{
  "flight-search-111": {
    "class": "baseline-pass",
    "score": 1.0,
    "detail": "All required tools and params present"
  },
  "flight-search-112": {
    "class": "baseline-pass",
    "score": 1.0,
    "detail": "All required tools and params present"
  },
  "flight-search-113": {
    "class": "baseline-pass",
    "score": 1.0,
    "detail": "All required tools and params present"
  },
  "flight-search-114": {
    "class": "baseline-pass",
    "score": 1.0,
    "detail": "All required tools and params present"
  },
  "flight-search-115": {
    "class": "baseline-fail",
    "score": 0.0,
    "detail": "avg=0.00 std=0.00 | The agent failed to ask for the number of passengers, which was explicitly stated as unknown in the "
  },
  "flight-search-116": {
    "class": "baseline-pass",
    "score": 1.0,
    "detail": "All required tools and params present"
  },
  "flight-search-117": {
    "class": "baseline-fail",
    "score": 0.75,
    "detail": "Missing params: ['search_flights.passengers', 'search_hotels.guests']"
  },
  "flight-search-118": {
    "class": "baseline-pass",
    "score": 1.0,
    "detail": "All required tools and params present"
  },
  "flight-search-119": {
    "class": "baseline-fail",
    "score": 0.0,
    "detail": "avg=0.00 std=0.00 | The agent failed to ask for a more specific date. Instead, it assumed a date (November 1, 2026), whi"
  },
  "flight-search-120": {
    "class": "baseline-pass",
    "score": 1.0,
    "detail": "All required tools and params present"
  }
}